fmtransfer/FmTransferWindow.py
fmtransfer/FmWindow.py
fmtransfer/Worker.py
fmtransfer/__init__.py
fmtransfer/__main__.py
led/__init__.py
led/led.py
tests/test_future.py
tests/test_multi.py
tests/test_threads.py
fm_transfer-0.1.13.dist-info/LICENSE
fm_transfer-0.1.13.dist-info/METADATA
fm_transfer-0.1.13.dist-info/WHEEL
fm_transfer-0.1.13.dist-info/entry_points.txt
fm_transfer-0.1.13.dist-info/top_level.txt
fm_transfer-0.1.13.dist-info/RECORD
