Metadata-Version: 2.1
Name: fm-transfer
Version: 0.1.13
Summary: Send and receive data via radio transceivers
Author-email: Matteo Tenca <matteo.tenca@gmail.com>
License:                     GNU GENERAL PUBLIC LICENSE
Project-URL: Repository, https://github.com/matteotenca/fm-transfer
Project-URL: Homepage, https://github.com/matteotenca/fm-transfer
Project-URL: Source, https://github.com/matteotenca/fm-transfer
Classifier: Development Status :: 5 - Production/Stable
Classifier: Intended Audience :: Developers
Classifier: Intended Audience :: Information Technology
Classifier: Programming Language :: Python :: 3.8
Classifier: Programming Language :: Python :: 3.9
Classifier: Programming Language :: Python :: 3.10
Classifier: Programming Language :: Python :: 3.11
Classifier: Programming Language :: Python :: 3.12
Classifier: Programming Language :: Python :: 3.13
Classifier: Topic :: Communications
Classifier: License :: OSI Approved :: GNU General Public License v3 or later (GPLv3+)
Requires-Python: >=3.8
License-File: LICENSE
Requires-Dist: pyqt6
Requires-Dist: quiet-transfer>=0.2.20
Provides-Extra: ggtransfer
Requires-Dist: gg-transfer>=0.2.13; extra == "ggtransfer"
